oxygenio/__init__.py
oxygenio/scripts.py
oxygenio/data/docs.txt
oxygenio-0.1.1.dist-info/METADATA
oxygenio-0.1.1.dist-info/WHEEL
oxygenio-0.1.1.dist-info/entry_points.txt
oxygenio-0.1.1.dist-info/top_level.txt
oxygenio-0.1.1.dist-info/RECORD
