Metadata-Version: 2.1
Name: oxygenio
Version: 0.1.1
Summary: GUI Development with Python, React and Typescript
Author-email: Esaú Mascarenhas <esaumasc@gmail.com>
License: MIT License
Project-URL: Homepage, https://github.com/EsauM10/oxygenio
Keywords: gui,eel,electron,typescript,javascript,react
Classifier: Development Status :: 3 - Alpha
Classifier: Programming Language :: Python :: 3.10
Classifier: Operating System :: OS Independent
Requires-Python: >=3.10
